<opinion>
<reporter_caption><center>SUPERIOR COURT OF PENNSYLVANIA, <citation>804 A.2d 52</citation> (Pa.Super. ____)</center></reporter_caption><court><center>Superior Court of Pennsylvania.</center>

</court>                   DECISIONS WITHOUT PUBLISHED OPINIONS

DOCKET NUMBER                       LOWER COURT AND                          DOCKET TITLE                     DISPOSITION     DATE         NUMBER/COUNTY

Com. v. Ciekalsky         01333MDA01      05/01/2002   1995-CR-0001508 Vacated and                  (Luzerne) Remanded

Com. v. Clark             01945WDA01      05/21/2002   199206324 Affirmed                     (Allegheny)

Com. v. Cleveland         01272MDA01      05/15/2002   01 So. 4 Affirmed                     (Lackawanna)

Com. v. Clore             02687EDA01      05/29/2002   3701-00 Affirmed                     (Delaware)

Com. v. Colson            01026EDA01      05/14/2002   CP 0008-1040 Affirmed                     (Philadelphia)

Com. v. Comstock          01207MDA01      05/21/2002   890 of 1998 Affirmed                     (Columbia)

Com. v. Crawford          00479MDA01      05/30/2002   1480 of 2000 Affirmed                     (Luzerne)

Com. v. Creighton<footnote_reference>[fn5]</footnote_reference>    02188EDA01      05/09/2002   2540-2545 Affirmed                     (Philadelphia)

Com. v. Cropp             01006WDA01      05/24/2002   211 of 1999 Affirmed                     (Fayette)

Com. v. Cruz              01345MDA01      05/15/2002   2001-0859 and Affirmed                     2001-0860 (Centre)

Com. v. D'Agostino        02668EDA01      05/21/2002   4405-98 Affirmed                     (Montgomery)

Com. v. Davis             02403EDA01      05/23/2002   3062-1999 Quashed                      (Northampton)

Com. v. Dawson            01747MDA00      05/01/2002   1232 CA 1999 Affirmed                     (York)

Com. v. DeFranco          01935WDA01      05/22/2002   1914 of 1982, Affirmed                     264 and 265 of 1983 (Erie)

Com. v. De Jesus          01478EDA01      05/21/2002   8205-3205 1/1 Affirmed                     (Philadelphia)

Com. v. Dezardo           00382WDA01      04/30/2002   3724 CRIMINAL 1999 Affirmed                     (Westmoreland)

Com. v. Diggs             00589MDA01      05/01/2002   1762 CD 1998 Affirmed                     (Dauphin)

Com. v. Dixon             00349EDA01      05/15/2002   9812-0905 1/1 Affirmed                     (Philadelphia)

Com. v. Dock              00488MDA01      05/03/2002   549 of 2000 Affirmed                     (Luzerne)

Com. v. Doran<footnote_reference>[fn6]</footnote_reference>        01136WDA01      05/08/2002   160 Crim 2001 Affirmed                     (Indiana)

Com. v. Dorundo           01131WDA01      05/06/2002   3030 C 2000 Affirmed                     (Westmoreland)

<footnote_body><footnote_number>[fn5]</footnote_number> Petition for reargument denied July 16, 2002.</footnote_body>

<footnote_body><footnote_number>[fn6]</footnote_number> Petition for reargument denied July 18, 2002.</footnote_body><page_number>Page 53</page_number>


</opinion>
